zenodotos/__init__.py
zenodotos/auth.py
zenodotos/client.py
zenodotos/config.py
zenodotos/exceptions.py
zenodotos/utils.py
zenodotos/cli/__init__.py
zenodotos/cli/commands.py
zenodotos/cli/navigation.py
zenodotos/cli/pagination.py
zenodotos/drive/__init__.py
zenodotos/drive/client.py
zenodotos/drive/models.py
zenodotos/formatters/__init__.py
zenodotos/formatters/display.py
zenodotos-0.2.12.dist-info/METADATA
zenodotos-0.2.12.dist-info/WHEEL
zenodotos-0.2.12.dist-info/entry_points.txt
zenodotos-0.2.12.dist-info/licenses/LICENSE
zenodotos-0.2.12.dist-info/RECORD
