Metadata-Version: 2.4
Name: zenodotos
Version: 0.2.12
Summary: A command-line interface tool for interacting with Google Drive
Author-email: Ignasi Fosch <natx@y10k.ws>
License-Expression: MIT
License-File: LICENSE
Requires-Python: <4.0,>=3.11
Requires-Dist: click>=8.1.7
Requires-Dist: google-api-python-client>=2.108.0
Requires-Dist: google-auth-httplib2>=0.1.1
Requires-Dist: google-auth-oauthlib>=1.1.0
Requires-Dist: pytest-cov>=6.2.1
Requires-Dist: pytest>=8.4.0
Requires-Dist: python-dateutil>=2.9.0.post0
Requires-Dist: pyyaml>=6.0.0
Requires-Dist: tomli-w>=1.0.0
Provides-Extra: dev
Requires-Dist: build>=1.0.0; extra == 'dev'
Requires-Dist: myst-parser>=3.0.1; extra == 'dev'
Requires-Dist: pre-commit>=3.6.0; extra == 'dev'
Requires-Dist: pytest-cov>=5.0.0; extra == 'dev'
Requires-Dist: pytest>=8.3.5; extra == 'dev'
Requires-Dist: ruff>=0.11.13; extra == 'dev'
Requires-Dist: sphinx-rtd-theme>=3.0.2; extra == 'dev'
Requires-Dist: sphinx>=7.1.2; extra == 'dev'
Requires-Dist: ty>=0.0.1a9; extra == 'dev'
